ecdata/__init__.py
ecdata-1.0.0.dist-info/LICENSE.txt
ecdata-1.0.0.dist-info/METADATA
ecdata-1.0.0.dist-info/WHEEL
ecdata-1.0.0.dist-info/top_level.txt
ecdata-1.0.0.dist-info/RECORD
